api_test_toolbox/result_toolbox.py
api_test_toolbox/assertion/toolbox_assertion.py
api_test_toolbox/enum/result_status_code_operator.py
api_test_toolbox-1.1.0.dist-info/licenses/LICENSE
api_test_toolbox-1.1.0.dist-info/METADATA
api_test_toolbox-1.1.0.dist-info/WHEEL
api_test_toolbox-1.1.0.dist-info/top_level.txt
api_test_toolbox-1.1.0.dist-info/RECORD
