Metadata-Version: 2.4
Name: api_test_toolbox
Version: 1.1.0
Summary: Several tools for testing API results on my FastAPI projects.
Author-email: Miguel <miguel@dacosys.com>
Project-URL: Repository, https://gitlab.com/dacosys_open/api_test_toolbox
Requires-Python: <4.0,>=3.9
License-File: LICENSE
Requires-Dist: requests
Requires-Dist: setuptools>=70.0.0
Requires-Dist: uvloop>=0.17.0; sys_platform != "win32"
Requires-Dist: httpx
Dynamic: license-file
